devopsprocessor/__init__.py
devopsprocessor/processor.py
devopsprocessor_ifn-0.1.0.dist-info/LICENSE
devopsprocessor_ifn-0.1.0.dist-info/METADATA
devopsprocessor_ifn-0.1.0.dist-info/WHEEL
devopsprocessor_ifn-0.1.0.dist-info/top_level.txt
devopsprocessor_ifn-0.1.0.dist-info/RECORD
