Metadata-Version: 2.1
Name: devopsprocessor-ifn
Version: 0.1.0
Summary: devops processor interface
Home-page: https://github.com/davengeo/devopsprocessor-ifn
Author: David Navarro Alvarez
Author-email: me@davengeo.com
License: UNKNOWN
Platform: UNKNOWN
Classifier: Development Status :: 4 - Beta
Classifier: License :: OSI Approved :: European Union Public Licence 1.2 (EUPL 1.2)
Classifier: Programming Language :: Python :: 3.8
Classifier: Topic :: System :: Systems Administration
License-File: LICENSE
Requires-Dist: cloudevents
